sphinx_tosca/__init__.py
sphinx_tosca/domain.py
sphinx_tosca-0.1.0.dist-info/DESCRIPTION.rst
sphinx_tosca-0.1.0.dist-info/METADATA
sphinx_tosca-0.1.0.dist-info/RECORD
sphinx_tosca-0.1.0.dist-info/WHEEL
sphinx_tosca-0.1.0.dist-info/metadata.json
sphinx_tosca-0.1.0.dist-info/pbr.json
sphinx_tosca-0.1.0.dist-info/top_level.txt
